cartograpy/__init__.py
cartograpy/boundaries.py
cartograpy/converter.py
cartograpy/countries_iso3.py
cartograpy/data.py
cartograpy/geocoder.py
cartograpy/iso3_codes.py
cartograpy/iso_code.py
cartograpy/mapper.py
cartograpy/processing.py
cartograpy/situation_map.py
cartograpy/styling.py
cartograpy/arrows/Arrow_01.svg
cartograpy/arrows/Arrow_02.svg
cartograpy/arrows/Arrow_03.svg
cartograpy/arrows/Arrow_04.svg
cartograpy/arrows/Arrow_05.svg
cartograpy/arrows/Arrow_06.svg
cartograpy/arrows/NorthArrow_01.svg
cartograpy/arrows/NorthArrow_02.svg
cartograpy/arrows/NorthArrow_03.svg
cartograpy/arrows/NorthArrow_04.svg
cartograpy/arrows/NorthArrow_05.svg
cartograpy/arrows/NorthArrow_06.svg
cartograpy/arrows/NorthArrow_07.svg
cartograpy/arrows/NorthArrow_08.svg
cartograpy/arrows/NorthArrow_09.svg
cartograpy/arrows/NorthArrow_10.svg
cartograpy/arrows/NorthArrow_11.svg
cartograpy-1.1.0.dist-info/licenses/LICENSE
cartograpy-1.1.0.dist-info/METADATA
cartograpy-1.1.0.dist-info/WHEEL
cartograpy-1.1.0.dist-info/top_level.txt
cartograpy-1.1.0.dist-info/RECORD
