Metadata-Version: 2.4
Name: cartograpy
Version: 1.1.0
Summary: Packages python pour créer des cartes
Home-page: https://github.com/mr-kam/cartograpy
Author: Anicet Cyrille Kambou
Author-email: Anicet Cyrille KAMBOU <kanicetcyrille@gmail.com>
License: MIT License
Project-URL: Homepage, https://mr-kam.github.io/cartograpy/
Project-URL: Repository, https://github.com/mr-kam/cartograpy
Project-URL: Documentation, https://mr-kam.github.io/cartograpy/
Project-URL: Bug Tracker, https://github.com/mr-kam/cartograpy/issues
Classifier: Programming Language :: Python :: 3
Classifier: License :: OSI Approved :: MIT License
Classifier: Operating System :: OS Independent
Classifier: Development Status :: 3 - Alpha
Classifier: Intended Audience :: Developers
Classifier: Topic :: Scientific/Engineering :: GIS
Requires-Python: >=3.7
License-File: LICENSE
Requires-Dist: cartopy>=0.24.0
Requires-Dist: geopandas==1.0.1
Requires-Dist: geojson==3.2.0
Requires-Dist: geopy>=2.4.0
Requires-Dist: shapely>=2.0.0
Requires-Dist: pyproj>=3.7.0
Requires-Dist: rasterio>=1.4.0
Requires-Dist: gpxpy>=1.6.0
Requires-Dist: pykml>=0.2.0
Requires-Dist: matplotlib==3.10.3
Requires-Dist: seaborn==0.13.0
Requires-Dist: pypalettes==0.1.6
Requires-Dist: pandas==2.2.3
Requires-Dist: numpy>=2.3.0
Requires-Dist: wbdata>=1.0.0
Requires-Dist: requests==2.32.4
Requires-Dist: requests-cache==1.2.1
Requires-Dist: pillow>=11.0.0
Requires-Dist: svglib>=1.5.0
Requires-Dist: reportlab[all]>=4.4.0
Requires-Dist: typing-extensions>=4.14.0
Requires-Dist: rlPyCairo==0.3.0
Requires-Dist: geodatasets==2024.8.0
Requires-Dist: mplcyberpunk==0.7.6
Requires-Dist: SciencePlots==2.1.1
Requires-Dist: osmnx==2.0.5
Provides-Extra: dev
Requires-Dist: pytest>=7.0.0; extra == "dev"
Requires-Dist: black>=23.0.0; extra == "dev"
Requires-Dist: flake8>=6.0.0; extra == "dev"
Requires-Dist: mypy>=1.0.0; extra == "dev"
Requires-Dist: jupyter>=1.0.0; extra == "dev"
Requires-Dist: jupyterlab>=4.0.0; extra == "dev"
Dynamic: author
Dynamic: home-page
Dynamic: license-file
